ReBench-1.3.0.data/scripts/denoise.py
rebench/__init__.py
rebench/configuration_error.py
rebench/configurator.py
rebench/denoise.py
rebench/denoise_client.py
rebench/environment.py
rebench/executor.py
rebench/output.py
rebench/persistence.py
rebench/rebench-schema.yml
rebench/rebench.py
rebench/rebenchdb.py
rebench/reporter.py
rebench/statistics.py
rebench/subprocess_kill.py
rebench/subprocess_with_timeout.py
rebench/ui.py
rebench/interop/__init__.py
rebench/interop/adapter.py
rebench/interop/jmh_adapter.py
rebench/interop/multivariate_adapter.py
rebench/interop/perf_adapter.py
rebench/interop/perf_parser.py
rebench/interop/plain_seconds_log_adapter.py
rebench/interop/rebench_log_adapter.py
rebench/interop/savina_log_adapter.py
rebench/interop/test_adapter.py
rebench/interop/test_vm_adapter.py
rebench/interop/time_adapter.py
rebench/interop/validation_log_adapter.py
rebench/model/__init__.py
rebench/model/benchmark.py
rebench/model/benchmark_suite.py
rebench/model/build_cmd.py
rebench/model/data_point.py
rebench/model/executor.py
rebench/model/exp_run_details.py
rebench/model/exp_variables.py
rebench/model/experiment.py
rebench/model/measurement.py
rebench/model/profile_data.py
rebench/model/profiler.py
rebench/model/reporting.py
rebench/model/run_id.py
rebench/model/termination_check.py
rebench/tests/bugs/__init__.py
rebench/tests/bugs/env_quote_test.py
rebench/tests/bugs/env_quote_vm.py
rebench/tests/bugs/issue_111_report_ignores_warmup_test.py
rebench/tests/bugs/issue_111_vm.py
rebench/tests/bugs/issue_112_invocations_setting_ignored_test.py
rebench/tests/bugs/issue_117_input_size_setting_ignored_test.py
rebench/tests/bugs/issue_27_invalid_run_not_handled_test.py
rebench/tests/bugs/issue_27_vm.py
rebench/tests/bugs/issue_4_run_equality_and_params_test.py
rebench/tests/bugs/issue_54_extra_args_test.py
rebench/tests/bugs/vm-one-result.py
rebench/tests/features/__init__.py
rebench/tests/features/ignore_timeouts_test.py
rebench/tests/features/ignore_timeouts_vm.py
ReBench-1.3.0.dist-info/AUTHORS.md
ReBench-1.3.0.dist-info/LICENSE
ReBench-1.3.0.dist-info/METADATA
ReBench-1.3.0.dist-info/WHEEL
ReBench-1.3.0.dist-info/entry_points.txt
ReBench-1.3.0.dist-info/top_level.txt
ReBench-1.3.0.dist-info/RECORD
