Metadata-Version: 2.2
Name: ReBench
Version: 1.3.0
Summary: Execute and document benchmarks reproducibly.
Home-page: https://github.com/smarr/ReBench
Author: Stefan Marr
Author-email: rebench@stefan-marr.de
License: MIT
License-File: LICENSE
License-File: AUTHORS.md
Requires-Dist: PyYAML>=6.0
Requires-Dist: pykwalify>=1.8.0
Requires-Dist: humanfriendly>=10.0
Requires-Dist: py-cpuinfo==9.0.0
Requires-Dist: psutil>=5.9.5
Dynamic: author
Dynamic: author-email
Dynamic: description
Dynamic: description-content-type
Dynamic: home-page
Dynamic: license
Dynamic: requires-dist
Dynamic: summary
